Workbook
Name FutureValue: Inputs!$B$15
Name InterestRate: Inputs!$B$8
Name LoanAmount: Inputs!$B$13
Name NumPeriods: Inputs!$B$9
Name Payment: Inputs!$B$14

Sheet README
A1: Interest Theory & Loan Modeling Toolkit
A2: Author : Brandon Bang Date Created : February 2026 Purpose : Excel-based financial mathematics toolkit aligned with SOA Exam FM concepts
A4: Project Overview This workbook implements core time value of money calculations used in actuarial and financial analysis. The model computes accumulation factors, discount factors, annuity present and future values, and loan amortization schedules. Sensitivity analysis allows evaluation of how interest rate and term assumptions affect financial outcomes.
B5: WorkSheet | C5: Descriptions
A6: How to Use the Model 1. Modify assumptions only in the Inputs worksheet 2. Do not overwrite formula cells 3. Outputs update automatically across all sheets 4. Review results in the Dashboard tab | B6: Inputs | C6: User-defined assumptions
B7: Factors | C7: Accumulation and discount factors
A8: Model Assumptions - interest rate represents effective rate per period - payments occur at regular intervals - loan uses level payments - no default or prepayment assumed - cash flows discounted using deterministic interest rate | B8: Annuities | C8: Annuity valuation calculations
B9: Loans | C9: Loan payment and amortization schedule
A10: Concepts Implemented - time value of money - discount factors - accumulation factors - annuity immediate and due - loan amortization - interest rate sensitivity analysis | B10: Sensitivity | C10: Scenario and rate analysis
B11: Dashboard | C11: Summary outputs and charts
A12: Technical Skills Demonstrated - advanced excel modeling - financial functions (PMT, PV, FV) - data tables and scenario analysis - structured spreadsheet design - dynamic dashboards
A14: Version History - (v1.0) Initial model creation

Sheet Inputs
A1: Interest Theory & Loan Modeling Toolkit
A2: User Input Panel
E3: Model Assumptions
A4: Last Updated | B4: =TODAY() -> 46076 | E4: Interest Rate Assumed Constant
E5: Payments occur end of period
E6: Level payments asumed
A7: Financial Assumptions | E7: No default or prepayment
A8: Interest Rate (i) | B8: 0.05 | C8: Effective Interest per Period
A9: Number of Periods (n) | B9: 10 | C9: Total Number of Payments
A10: Compounding Periods | B10: Annual | C10: Assumption
A12: Cashflow / Loan Inputs
A13: Loan Amount (PV) | B13: 10000 | C13: Initial Loan Princial
A14: Payment Amount | B14: 1000 | C14: Level Payment each Period
A15: Future Value Target | B15: 0 | C15: Ending Balance

Sheet Factors
A1: Interest Accumulatio & Discount Factors
A3: Interest Rate (i) | B3: =Inputs!B8 -> 0.05 | D3: t | E3: (1+i)^t | F3: v^t
A4: Number of Periods (n) | B4: =Inputs!B9 -> 10 | D4: 0 | E4: =(1+$B$3)^D4 -> 1 | F4: =(1/(1+$B$3))^D4 -> 1
D5: 1 | E5: =(1+$B$3)^D5 -> 1.05 | F5: =(1/(1+$B$3))^D5 -> 0.95238095
A6: Accumulation Factor (1+i)^n | B6: =(1+B3)^B4 -> 1.6288946 | D6: 2 | E6: =(1+$B$3)^D6 -> 1.1025 | F6: =(1/(1+$B$3))^D6 -> 0.90702948
A7: Discount Factor v | B7: =1/(1+B3) -> 0.95238095 | D7: 3 | E7: =(1+$B$3)^D7 -> 1.157625 | F7: =(1/(1+$B$3))^D7 -> 0.8638376
A8: v^n | B8: =B7^B4 -> 0.61391325 | D8: 4 | E8: =(1+$B$3)^D8 -> 1.2155063 | F8: =(1/(1+$B$3))^D8 -> 0.82270247
D9: 5 | E9: =(1+$B$3)^D9 -> 1.2762816 | F9: =(1/(1+$B$3))^D9 -> 0.78352617
D10: 6 | E10: =(1+$B$3)^D10 -> 1.3400956 | F10: =(1/(1+$B$3))^D10 -> 0.7462154
D11: 7 | E11: =(1+$B$3)^D11 -> 1.4071004 | F11: =(1/(1+$B$3))^D11 -> 0.71068133
D12: 8 | E12: =(1+$B$3)^D12 -> 1.4774554 | F12: =(1/(1+$B$3))^D12 -> 0.67683936
D13: 9 | E13: =(1+$B$3)^D13 -> 1.5513282 | F13: =(1/(1+$B$3))^D13 -> 0.64460892
D14: 10 | E14: =(1+$B$3)^D14 -> 1.6288946 | F14: =(1/(1+$B$3))^D14 -> 0.61391325
D15: 11 | E15: =(1+$B$3)^D15 -> 1.7103394 | F15: =(1/(1+$B$3))^D15 -> 0.58467929
D16: 12 | E16: =(1+$B$3)^D16 -> 1.7958563 | F16: =(1/(1+$B$3))^D16 -> 0.55683742
D17: 13 | E17: =(1+$B$3)^D17 -> 1.8856491 | F17: =(1/(1+$B$3))^D17 -> 0.53032135
D18: 14 | E18: =(1+$B$3)^D18 -> 1.9799316 | F18: =(1/(1+$B$3))^D18 -> 0.50506795
D19: 15 | E19: =(1+$B$3)^D19 -> 2.0789282 | F19: =(1/(1+$B$3))^D19 -> 0.4810171
D20: 16 | E20: =(1+$B$3)^D20 -> 2.1828746 | F20: =(1/(1+$B$3))^D20 -> 0.45811152
... D24: 20 | E24: =(1+$B$3)^D24 -> 2.6532977 | F24: =(1/(1+$B$3))^D24 -> 0.37688948

Sheet Annuities
A1: Annuity Valuation Calculations
A3: Interest Rate (i) | B3: =InterestRate -> 0.05
A4: Number of Periods (n) | B4: =NumPeriods -> 10
A5: Payment (PMT) | B5: =Payment -> 1000
A7: Annuity Immediate
A8: PV Annuity Immediate | B8: =(1-(1+B3)^(-B4))/B3 -> 7.7217349
A9: PV of Payments | B9: =B5*B8 -> 7721.7349
A11: FV Annuity Immediate | B11: =((1+B3)^B4-1)/B3 -> 12.577893
A12: Future Value of Payments | B12: =B5*B11 -> 12577.893
A14: Annuity Due
A15: PV Annuity Due | B15: =B8*(1+B3) -> 8.1078217
A16: PV Payments (Due) | B16: =B5*B15 -> 8107.8217
A18: FV Annuity Due | B18: =B11*(1+B3) -> 13.206787
A19: FV Payments (Due) | B19: =B5*B18 -> 13206.787

Sheet Loans
A1: Loan Amortization Model
A3: Interest Rate | B3: =Sensitivity!B3 -> 0.05
A4: Number of Periods | B4: =NumPeriods -> 10
A5: Loan Amount | B5: =LoanAmount -> 10000
A7: Level Payment | B7: =PMT(B3, B4, -B5) -> 1295.0457
A10: Period | B10: Payment | C10: Interest | D10: Principal | E10: Balance
A11: 1 | B11: =$B$7 -> 1295.0457 | C11: =E11*$B$3 -> 500 | D11: =B11-C11 -> 795.04575 | E11: =B5 -> 10000
A12: =A11+1 -> 2 | B12: =$B$7 -> 1295.0457 | C12: =E12*$B$3 -> 460.24771 | D12: =B12-C12 -> 834.79804 | E12: =E11-D11 -> 9204.9543
A13: =A12+1 -> 3 | B13: =$B$7 -> 1295.0457 | C13: =E13*$B$3 -> 418.50781 | D13: =B13-C13 -> 876.53794 | E13: =E12-D12 -> 8370.1562
A14: =A13+1 -> 4 | B14: =$B$7 -> 1295.0457 | C14: =E14*$B$3 -> 374.68091 | D14: =B14-C14 -> 920.36484 | E14: =E13-D13 -> 7493.6183
A15: =A14+1 -> 5 | B15: =$B$7 -> 1295.0457 | C15: =E15*$B$3 -> 328.66267 | D15: =B15-C15 -> 966.38308 | E15: =E14-D14 -> 6573.2534
A16: =A15+1 -> 6 | B16: =$B$7 -> 1295.0457 | C16: =E16*$B$3 -> 280.34352 | D16: =B16-C16 -> 1014.7022 | E16: =E15-D15 -> 5606.8704
A17: =A16+1 -> 7 | B17: =$B$7 -> 1295.0457 | C17: =E17*$B$3 -> 229.60841 | D17: =B17-C17 -> 1065.4373 | E17: =E16-D16 -> 4592.1681
A18: =A17+1 -> 8 | B18: =$B$7 -> 1295.0457 | C18: =E18*$B$3 -> 176.33654 | D18: =B18-C18 -> 1118.7092 | E18: =E17-D17 -> 3526.7308
A19: =A18+1 -> 9 | B19: =$B$7 -> 1295.0457 | C19: =E19*$B$3 -> 120.40108 | D19: =B19-C19 -> 1174.6447 | E19: =E18-D18 -> 2408.0216
A20: =A19+1 -> 10 | B20: =$B$7 -> 1295.0457 | C20: =E20*$B$3 -> 61.668845 | D20: =B20-C20 -> 1233.3769 | E20: =E19-D19 -> 1233.3769
A22: Total Interest Paid | B22: =SUM(C11:C20) -> 2950.4575
A23: Total Payments | B23: =SUM(B11:B20) -> 12950.457

Sheet Sensitivity
A1: Interest Rate - Sensitivity - Loan Payments
A3: Scenario Interest Rate | B3: =Inputs!B8 -> 0.05
A4: Loan Payment Output | B4: =Loans!B7 -> 1295.0457
A7: Interest Rate | B7: =B4 -> 1295.0457
A8: 0.03 | B8: 1172.3051
A9: 0.04 | B9: 1232.9094
A10: 0.05 | B10: 1295.0457
A11: 0.06 | B11: 1358.6796
A12: 0.07 | B12: 1423.775
A13: 0.08 | B13: 1490.2949

Sheet Dashboard
A1: Acturial Interest & Loan Modeling Dashboard
A3: Model Inputs | D3: Key Results
A4: Interest Rate | B4: =Inputs!B8 -> 0.05 | D4: Total Payments | E4: =Loans!B23 -> 12950.457
A5: Loan Amount | B5: =Inputs!B13 -> 10000 | D5: Total Interest Paid | E5: =Loans!B22 -> 2950.4575
A6: Number of Periods | B6: =Inputs!B9 -> 10 | D6: Ending Loan Balance | E6: =Loans!E20 -> 1233.3769
A7: Payments | B7: =Loans!B7 -> 1295.0457
A9: Loan Amortization Chart
A26: Built in Excel using actuarial interest theory, annuity valuation, loan amortization modeling, and sensitivity analysis.
